uvicorn_manager/__init__.py
uvicorn_manager/py.typed
uvicorn_manager-0.0.0.dist-info/METADATA
uvicorn_manager-0.0.0.dist-info/WHEEL
uvicorn_manager-0.0.0.dist-info/RECORD
