Metadata-Version: 2.1
Name: uvicorn-manager
Version: 0.0.0
Summary: Process manager for Uvicorn processes! :worker:
Author-email: Marcelo Trylesinski <marcelotryle@gmail.com>
License: MIT
